my_happy_modin/__init__.py
my_happy_modin/_version.py
my_happy_modin/error_message.py
my_happy_modin/utils.py
my_happy_modin/backends/__init__.py
my_happy_modin/backends/base/__init__.py
my_happy_modin/backends/base/query_compiler.py
my_happy_modin/backends/pandas/__init__.py
my_happy_modin/backends/pandas/parsers.py
my_happy_modin/backends/pandas/query_compiler.py
my_happy_modin/backends/pyarrow/__init__.py
my_happy_modin/backends/pyarrow/parsers.py
my_happy_modin/backends/pyarrow/query_compiler.py
my_happy_modin/config/__init__.py
my_happy_modin/config/envvars.py
my_happy_modin/config/pubsub.py
my_happy_modin/data_management/__init__.py
my_happy_modin/data_management/utils.py
my_happy_modin/data_management/factories/__init__.py
my_happy_modin/data_management/factories/dispatcher.py
my_happy_modin/data_management/factories/factories.py
my_happy_modin/data_management/functions/__init__.py
my_happy_modin/data_management/functions/binary_function.py
my_happy_modin/data_management/functions/foldfunction.py
my_happy_modin/data_management/functions/function.py
my_happy_modin/data_management/functions/groupby_function.py
my_happy_modin/data_management/functions/mapfunction.py
my_happy_modin/data_management/functions/mapreducefunction.py
my_happy_modin/data_management/functions/reductionfunction.py
my_happy_modin/data_management/functions/default_methods/__init__.py
my_happy_modin/data_management/functions/default_methods/any_default.py
my_happy_modin/data_management/functions/default_methods/binary_default.py
my_happy_modin/data_management/functions/default_methods/cat_default.py
my_happy_modin/data_management/functions/default_methods/dataframe_default.py
my_happy_modin/data_management/functions/default_methods/datetime_default.py
my_happy_modin/data_management/functions/default_methods/default.py
my_happy_modin/data_management/functions/default_methods/groupby_default.py
my_happy_modin/data_management/functions/default_methods/resample_default.py
my_happy_modin-0.8.21.dist-info/LICENSE
my_happy_modin-0.8.21.dist-info/METADATA
my_happy_modin-0.8.21.dist-info/WHEEL
my_happy_modin-0.8.21.dist-info/top_level.txt
my_happy_modin-0.8.21.dist-info/RECORD
