Metadata-Version: 2.1
Name: my-happy-modin
Version: 0.8.21
Summary: The simple version for modin.
Home-page: https://github.com/ggservice007/my-happy-modin
Author: ggservice007
Author-email: ggservice007@126.com
License: Apache 2
Platform: UNKNOWN
Requires-Python: >=3.7.7
Requires-Dist: ray (>=1.1.0)
Requires-Dist: my-happy-pandas (>=1.1.10)
